ohnoyoudidnt/__init__.py
ohnoyoudidnt/checks.py
ohnoyoudidnt-0.1.dist-info/METADATA
ohnoyoudidnt-0.1.dist-info/WHEEL
ohnoyoudidnt-0.1.dist-info/entry_points.txt
ohnoyoudidnt-0.1.dist-info/top_level.txt
ohnoyoudidnt-0.1.dist-info/RECORD
