Metadata-Version: 2.1
Name: ohnoyoudidnt
Version: 0.1
Summary: doc8 linter for frc-docs
Home-page: https://github.com/wpilibsuite/ohnoyoudidnt
Author: Vasista Vovveti
Author-email: vasistavovveti@gmail.com
License: UNKNOWN
Platform: UNKNOWN
Classifier: Environment :: Plugins
Classifier: Environment :: Web Environment
Classifier: Framework :: Sphinx :: Extension
Classifier: Intended Audience :: Developers
Classifier: License :: OSI Approved :: MIT License
Classifier: Natural Language :: English
Classifier: Operating System :: OS Independent
Classifier: Programming Language :: Python :: 3.6
Classifier: Programming Language :: Python :: 3.7
Classifier: Programming Language :: Python :: 3.8
Classifier: Programming Language :: Python
Classifier: Topic :: Documentation :: Sphinx
Classifier: Topic :: Documentation
Classifier: Topic :: Software Development :: Documentation
Classifier: Topic :: Text Processing
Classifier: Topic :: Utilities
Requires-Dist: more-itertools (>=8.6.0)
Requires-Dist: doc8 (>=0.8.1)
Requires-Dist: docutils (>=0.16)
